{
  "color": {
    "link": {
      "25": {
        "description": "",
        "type": "color",
        "value": "#f5faffff",
        "blendMode": "normal",
        "extensions": {
          "org.lukasoppermann.figmaDesignTokens": {
            "styleId": "S:1475475b3b8fcce9ecdd695cd51472dcfd6cd7f3,",
            "exportKey": "color"
          }
        }
      },
      "50": {
        "description": "",
        "type": "color",
        "value": "#eff8ffff",
        "blendMode": "normal",
        "extensions": {
          "org.lukasoppermann.figmaDesignTokens": {
            "styleId": "S:13d64152ca213635f32b7166b6a1e175576884dc,",
            "exportKey": "color"
          }
        }
      },
      "100": {
        "description": "",
        "type": "color",
        "value": "#d1e9ffff",
        "blendMode": "normal",
        "extensions": {
          "org.lukasoppermann.figmaDesignTokens": {
            "styleId": "S:8f97f771e0cf6b21c3ba62b38d3fe0209a7ba901,",
            "exportKey": "color"
          }
        }
      },
      "200": {
        "description": "",
        "type": "color",
        "value": "#b2ddffff",
        "blendMode": "normal",
        "extensions": {
          "org.lukasoppermann.figmaDesignTokens": {
            "styleId": "S:dc5a2d5ecfc34d9deff1138a9a69967d2ae965c8,",
            "exportKey": "color"
          }
        }
      },
      "300": {
        "description": "",
        "type": "color",
        "value": "#84caffff",
        "blendMode": "normal",
        "extensions": {
          "org.lukasoppermann.figmaDesignTokens": {
            "styleId": "S:4aa3784d361d2f48c621797fff6035fa5871e0d5,",
            "exportKey": "color"
          }
        }
      },
      "400": {
        "description": "",
        "type": "color",
        "value": "#53b1fdff",
        "blendMode": "normal",
        "extensions": {
          "org.lukasoppermann.figmaDesignTokens": {
            "styleId": "S:690ff4df44ab86b00b42e21bac05273cf4e97424,",
            "exportKey": "color"
          }
        }
      },
      "500": {
        "description": "",
        "type": "color",
        "value": "#2e90faff",
        "blendMode": "normal",
        "extensions": {
          "org.lukasoppermann.figmaDesignTokens": {
            "styleId": "S:154004b98f2442f8808cebdfca72456696560083,",
            "exportKey": "color"
          }
        }
      },
      "600": {
        "description": "",
        "type": "color",
        "value": "#1570efff",
        "blendMode": "normal",
        "extensions": {
          "org.lukasoppermann.figmaDesignTokens": {
            "styleId": "S:273a57b55d61b1d4bec198fb07826ba651dc0b60,",
            "exportKey": "color"
          }
        }
      },
      "700": {
        "description": "",
        "type": "color",
        "value": "#175cd3ff",
        "blendMode": "normal",
        "extensions": {
          "org.lukasoppermann.figmaDesignTokens": {
            "styleId": "S:66042972968410e9b47becbb8d04a40ef53373b2,",
            "exportKey": "color"
          }
        }
      },
      "800": {
        "description": "",
        "type": "color",
        "value": "#1849a9ff",
        "blendMode": "normal",
        "extensions": {
          "org.lukasoppermann.figmaDesignTokens": {
            "styleId": "S:73ac8dc741a4eefb0bb152880c260058273d8448,",
            "exportKey": "color"
          }
        }
      },
      "900": {
        "description": "",
        "type": "color",
        "value": "#194185ff",
        "blendMode": "normal",
        "extensions": {
          "org.lukasoppermann.figmaDesignTokens": {
            "styleId": "S:507f75cceae698ddf2cbb27f4ae2d7679b787a44,",
            "exportKey": "color"
          }
        }
      }
    },
    "success": {
      "25": {
        "description": "",
        "type": "color",
        "value": "#f6fef9ff",
        "blendMode": "normal",
        "extensions": {
          "org.lukasoppermann.figmaDesignTokens": {
            "styleId": "S:5e0273e09e2ad388b051a2ea56f4edbfc8d7e89d,",
            "exportKey": "color"
          }
        }
      },
      "50": {
        "description": "",
        "type": "color",
        "value": "#ecfdf3ff",
        "blendMode": "normal",
        "extensions": {
          "org.lukasoppermann.figmaDesignTokens": {
            "styleId": "S:c6ec68e94b33f2b7ad5c52711d7aa25197552cac,",
            "exportKey": "color"
          }
        }
      },
      "100": {
        "description": "",
        "type": "color",
        "value": "#d1fadfff",
        "blendMode": "normal",
        "extensions": {
          "org.lukasoppermann.figmaDesignTokens": {
            "styleId": "S:9a6119de664564e35fcf290822852b86bbedcdd5,",
            "exportKey": "color"
          }
        }
      },
      "200": {
        "description": "",
        "type": "color",
        "value": "#a6f4c5ff",
        "blendMode": "normal",
        "extensions": {
          "org.lukasoppermann.figmaDesignTokens": {
            "styleId": "S:a1eea4e55fd180bcba7eb79003150236223ba80e,",
            "exportKey": "color"
          }
        }
      },
      "300": {
        "description": "",
        "type": "color",
        "value": "#6ce9a6ff",
        "blendMode": "normal",
        "extensions": {
          "org.lukasoppermann.figmaDesignTokens": {
            "styleId": "S:7def20e2052c2e703b22450d09d9d4b113a45ae3,",
            "exportKey": "color"
          }
        }
      },
      "400": {
        "description": "",
        "type": "color",
        "value": "#32d583ff",
        "blendMode": "normal",
        "extensions": {
          "org.lukasoppermann.figmaDesignTokens": {
            "styleId": "S:fade40a54052debbe4c247346f2ab1afac656f88,",
            "exportKey": "color"
          }
        }
      },
      "500": {
        "description": "",
        "type": "color",
        "value": "#12b76aff",
        "blendMode": "normal",
        "extensions": {
          "org.lukasoppermann.figmaDesignTokens": {
            "styleId": "S:e27f380fd6912d3b0fd4bea51d1a5af2a8dc1532,",
            "exportKey": "color"
          }
        }
      },
      "600": {
        "description": "",
        "type": "color",
        "value": "#039855ff",
        "blendMode": "normal",
        "extensions": {
          "org.lukasoppermann.figmaDesignTokens": {
            "styleId": "S:aded65120f723c86473ee9cce045aa07fb596fc2,",
            "exportKey": "color"
          }
        }
      },
      "700": {
        "description": "",
        "type": "color",
        "value": "#027a48ff",
        "blendMode": "normal",
        "extensions": {
          "org.lukasoppermann.figmaDesignTokens": {
            "styleId": "S:90c822d64cd8d4c8cc1b44c13007790bcaac4aea,",
            "exportKey": "color"
          }
        }
      },
      "800": {
        "description": "",
        "type": "color",
        "value": "#05603aff",
        "blendMode": "normal",
        "extensions": {
          "org.lukasoppermann.figmaDesignTokens": {
            "styleId": "S:b8796f5c736fa6d9864c74db729d95ffa1a54a1c,",
            "exportKey": "color"
          }
        }
      },
      "900": {
        "description": "",
        "type": "color",
        "value": "#054f31ff",
        "blendMode": "normal",
        "extensions": {
          "org.lukasoppermann.figmaDesignTokens": {
            "styleId": "S:ef817b5169266b480029bf328385714566e757e4,",
            "exportKey": "color"
          }
        }
      }
    },
    "warning": {
      "25": {
        "description": "",
        "type": "color",
        "value": "#fffcf5ff",
        "blendMode": "normal",
        "extensions": {
          "org.lukasoppermann.figmaDesignTokens": {
            "styleId": "S:19790be03dbd4cdd80505f92690f8e1b713a8af7,",
            "exportKey": "color"
          }
        }
      },
      "50": {
        "description": "",
        "type": "color",
        "value": "#fffaebff",
        "blendMode": "normal",
        "extensions": {
          "org.lukasoppermann.figmaDesignTokens": {
            "styleId": "S:ad93bc9510a456be2018bd4a8bffa29ab959871a,",
            "exportKey": "color"
          }
        }
      },
      "100": {
        "description": "",
        "type": "color",
        "value": "#fef0c7ff",
        "blendMode": "normal",
        "extensions": {
          "org.lukasoppermann.figmaDesignTokens": {
            "styleId": "S:a7657b9f3a819e3a522ec9c69d2bca4440e20032,",
            "exportKey": "color"
          }
        }
      },
      "200": {
        "description": "",
        "type": "color",
        "value": "#fedf89ff",
        "blendMode": "normal",
        "extensions": {
          "org.lukasoppermann.figmaDesignTokens": {
            "styleId": "S:0255937e732bff834ac931279df4dde5e2d3687b,",
            "exportKey": "color"
          }
        }
      },
      "300": {
        "description": "",
        "type": "color",
        "value": "#fec84bff",
        "blendMode": "normal",
        "extensions": {
          "org.lukasoppermann.figmaDesignTokens": {
            "styleId": "S:40da1b873818b0f0a61e9092a32235d65214b246,",
            "exportKey": "color"
          }
        }
      },
      "400": {
        "description": "",
        "type": "color",
        "value": "#fdb022ff",
        "blendMode": "normal",
        "extensions": {
          "org.lukasoppermann.figmaDesignTokens": {
            "styleId": "S:4106e8f05c116c2695c5529ec10cedff928f5841,",
            "exportKey": "color"
          }
        }
      },
      "500": {
        "description": "",
        "type": "color",
        "value": "#f79009ff",
        "blendMode": "normal",
        "extensions": {
          "org.lukasoppermann.figmaDesignTokens": {
            "styleId": "S:81386339aaf9a9da9e1f21a17b835d45eaa9ed8d,",
            "exportKey": "color"
          }
        }
      },
      "600": {
        "description": "",
        "type": "color",
        "value": "#dc6803ff",
        "blendMode": "normal",
        "extensions": {
          "org.lukasoppermann.figmaDesignTokens": {
            "styleId": "S:e09f971ea7af992587bb9990fd12f61e0785168b,",
            "exportKey": "color"
          }
        }
      },
      "700": {
        "description": "",
        "type": "color",
        "value": "#b54708ff",
        "blendMode": "normal",
        "extensions": {
          "org.lukasoppermann.figmaDesignTokens": {
            "styleId": "S:60c3fd9b7a013ec811cf5cb60bd84ed62aa9ce9c,",
            "exportKey": "color"
          }
        }
      },
      "800": {
        "description": "",
        "type": "color",
        "value": "#93370dff",
        "blendMode": "normal",
        "extensions": {
          "org.lukasoppermann.figmaDesignTokens": {
            "styleId": "S:fa1898a24f656243a0af10234a9fc892355fa8b1,",
            "exportKey": "color"
          }
        }
      },
      "900": {
        "description": "",
        "type": "color",
        "value": "#7a2e0eff",
        "blendMode": "normal",
        "extensions": {
          "org.lukasoppermann.figmaDesignTokens": {
            "styleId": "S:faba3024c8439e37f619d9d00a668457a154e18f,",
            "exportKey": "color"
          }
        }
      }
    },
    "error": {
      "25": {
        "description": "",
        "type": "color",
        "value": "#fffbfaff",
        "blendMode": "normal",
        "extensions": {
          "org.lukasoppermann.figmaDesignTokens": {
            "styleId": "S:542f31355f7ebb0fc6d856e2e6a8a1698aa550e3,",
            "exportKey": "color"
          }
        }
      },
      "50": {
        "description": "",
        "type": "color",
        "value": "#fef3f2ff",
        "blendMode": "normal",
        "extensions": {
          "org.lukasoppermann.figmaDesignTokens": {
            "styleId": "S:29e079b103ec22d981b2e5126adef10187e4106c,",
            "exportKey": "color"
          }
        }
      },
      "100": {
        "description": "",
        "type": "color",
        "value": "#fee4e2ff",
        "blendMode": "normal",
        "extensions": {
          "org.lukasoppermann.figmaDesignTokens": {
            "styleId": "S:db15372b64a0a0fa15e05e706f8ff29d63974f39,",
            "exportKey": "color"
          }
        }
      },
      "200": {
        "description": "",
        "type": "color",
        "value": "#fecdcaff",
        "blendMode": "normal",
        "extensions": {
          "org.lukasoppermann.figmaDesignTokens": {
            "styleId": "S:7ee94777bad8c4059dd549ede1fa9b1bae0a6ab1,",
            "exportKey": "color"
          }
        }
      },
      "300": {
        "description": "",
        "type": "color",
        "value": "#fda29bff",
        "blendMode": "normal",
        "extensions": {
          "org.lukasoppermann.figmaDesignTokens": {
            "styleId": "S:6ed1e99be156a3528d019d5c8b1e728dd038a84e,",
            "exportKey": "color"
          }
        }
      },
      "400": {
        "description": "",
        "type": "color",
        "value": "#f97066ff",
        "blendMode": "normal",
        "extensions": {
          "org.lukasoppermann.figmaDesignTokens": {
            "styleId": "S:eb3c5c2a864a2f98faed3007a5cc285ce4816785,",
            "exportKey": "color"
          }
        }
      },
      "500": {
        "description": "",
        "type": "color",
        "value": "#f04438ff",
        "blendMode": "normal",
        "extensions": {
          "org.lukasoppermann.figmaDesignTokens": {
            "styleId": "S:8fceb1ee603622d76d652a54ce7d5236e47fb526,",
            "exportKey": "color"
          }
        }
      },
      "600": {
        "description": "",
        "type": "color",
        "value": "#d92d20ff",
        "blendMode": "normal",
        "extensions": {
          "org.lukasoppermann.figmaDesignTokens": {
            "styleId": "S:a1ca66eb6b79984eb4ff97da52315bcbcdf812f8,",
            "exportKey": "color"
          }
        }
      },
      "700": {
        "description": "",
        "type": "color",
        "value": "#b42318ff",
        "blendMode": "normal",
        "extensions": {
          "org.lukasoppermann.figmaDesignTokens": {
            "styleId": "S:725f6dea430cef2d42a3bb9b00f7a050dcf4e6e6,",
            "exportKey": "color"
          }
        }
      },
      "800": {
        "description": "",
        "type": "color",
        "value": "#912018ff",
        "blendMode": "normal",
        "extensions": {
          "org.lukasoppermann.figmaDesignTokens": {
            "styleId": "S:711400b7a3600427b4ab6eb763c20e7c6c84092b,",
            "exportKey": "color"
          }
        }
      },
      "900": {
        "description": "",
        "type": "color",
        "value": "#7a271aff",
        "blendMode": "normal",
        "extensions": {
          "org.lukasoppermann.figmaDesignTokens": {
            "styleId": "S:88454422927a518b15ac5adb221dea52254a42e8,",
            "exportKey": "color"
          }
        }
      }
    },
    "primary": {
      "25": {
        "description": "",
        "type": "color",
        "value": "#fffcf2ff",
        "blendMode": "normal",
        "extensions": {
          "org.lukasoppermann.figmaDesignTokens": {
            "styleId": "S:fc2570c695c60f3d1a97261a2f770e4f1a4d48c8,",
            "exportKey": "color"
          }
        }
      },
      "50": {
        "description": "",
        "type": "color",
        "value": "#fef8ddff",
        "blendMode": "normal",
        "extensions": {
          "org.lukasoppermann.figmaDesignTokens": {
            "styleId": "S:561eec8fc702c9386353f2d1cfb24db7382ef898,",
            "exportKey": "color"
          }
        }
      },
      "100": {
        "description": "",
        "type": "color",
        "value": "#fef5cbff",
        "blendMode": "normal",
        "extensions": {
          "org.lukasoppermann.figmaDesignTokens": {
            "styleId": "S:9a2bd8f8218d4d420849862aeb4d2cafcb4a186a,",
            "exportKey": "color"
          }
        }
      },
      "200": {
        "description": "",
        "type": "color",
        "value": "#ffeb74ff",
        "blendMode": "normal",
        "extensions": {
          "org.lukasoppermann.figmaDesignTokens": {
            "styleId": "S:03bef83f7e6b929dc558de8409900af0797618be,",
            "exportKey": "color"
          }
        }
      },
      "300": {
        "description": "",
        "type": "color",
        "value": "#ffdd00ff",
        "blendMode": "normal",
        "extensions": {
          "org.lukasoppermann.figmaDesignTokens": {
            "styleId": "S:d3b928f196f5a7b5d3b9fdd48e00d40578d47cd1,",
            "exportKey": "color"
          }
        }
      },
      "400": {
        "description": "",
        "type": "color",
        "value": "#f9ca02ff",
        "blendMode": "normal",
        "extensions": {
          "org.lukasoppermann.figmaDesignTokens": {
            "styleId": "S:92042f8967c3a348a58de30556f1bf31ceb5eaae,",
            "exportKey": "color"
          }
        }
      },
      "500": {
        "description": "",
        "type": "color",
        "value": "#f2b705ff",
        "blendMode": "normal",
        "extensions": {
          "org.lukasoppermann.figmaDesignTokens": {
            "styleId": "S:3a8f1b97af9ba4b7895ac69918cbc69d655fd5ad,",
            "exportKey": "color"
          }
        }
      },
      "600": {
        "description": "",
        "type": "color",
        "value": "#f0b305ff",
        "blendMode": "normal",
        "extensions": {
          "org.lukasoppermann.figmaDesignTokens": {
            "styleId": "S:eccd3d7ff4bc6d2f7a3c96cf858bdcbab4aa3712,",
            "exportKey": "color"
          }
        }
      },
      "700": {
        "description": "",
        "type": "color",
        "value": "#e9a405ff",
        "blendMode": "normal",
        "extensions": {
          "org.lukasoppermann.figmaDesignTokens": {
            "styleId": "S:6c76fde096b0e96b124a10cd208209c9070bb92d,",
            "exportKey": "color"
          }
        }
      },
      "800": {
        "description": "",
        "type": "color",
        "value": "#e29606ff",
        "blendMode": "normal",
        "extensions": {
          "org.lukasoppermann.figmaDesignTokens": {
            "styleId": "S:7d598ef796e7d3fb6c209210ef61bfe17b653e0d,",
            "exportKey": "color"
          }
        }
      },
      "900": {
        "description": "",
        "type": "color",
        "value": "#d17407ff",
        "blendMode": "normal",
        "extensions": {
          "org.lukasoppermann.figmaDesignTokens": {
            "styleId": "S:c27d7f396c1844db682e60d6ed1d87524bd056d1,",
            "exportKey": "color"
          }
        }
      }
    },
    "gray": {
      "25": {
        "description": "",
        "type": "color",
        "value": "#fcfcfdff",
        "blendMode": "normal",
        "extensions": {
          "org.lukasoppermann.figmaDesignTokens": {
            "styleId": "S:02a8515f794ac129d636363ca284f6f5e0b368b1,",
            "exportKey": "color"
          }
        }
      },
      "50": {
        "description": "",
        "type": "color",
        "value": "#f9fafbff",
        "blendMode": "normal",
        "extensions": {
          "org.lukasoppermann.figmaDesignTokens": {
            "styleId": "S:80fe9cad4b6b40880557b8bc8b5958c9950f5ec4,",
            "exportKey": "color"
          }
        }
      },
      "100": {
        "description": "",
        "type": "color",
        "value": "#f2f4f7ff",
        "blendMode": "normal",
        "extensions": {
          "org.lukasoppermann.figmaDesignTokens": {
            "styleId": "S:2e373c21dbd7e0d2c5604367c51cfd40ba3160fa,",
            "exportKey": "color"
          }
        }
      },
      "200": {
        "description": "",
        "type": "color",
        "value": "#eaecf0ff",
        "blendMode": "normal",
        "extensions": {
          "org.lukasoppermann.figmaDesignTokens": {
            "styleId": "S:0a6528720f1274a610e7f5c74c0e2d3e4c2fc620,",
            "exportKey": "color"
          }
        }
      },
      "300": {
        "description": "",
        "type": "color",
        "value": "#d0d5ddff",
        "blendMode": "normal",
        "extensions": {
          "org.lukasoppermann.figmaDesignTokens": {
            "styleId": "S:a258db11009ce5fd80dba06580e2edc5d91800fb,",
            "exportKey": "color"
          }
        }
      },
      "400": {
        "description": "",
        "type": "color",
        "value": "#98a2b3ff",
        "blendMode": "normal",
        "extensions": {
          "org.lukasoppermann.figmaDesignTokens": {
            "styleId": "S:042ac6a6597243bb66fdf6ac9e6c0a2608814059,",
            "exportKey": "color"
          }
        }
      },
      "500": {
        "description": "",
        "type": "color",
        "value": "#667085ff",
        "blendMode": "normal",
        "extensions": {
          "org.lukasoppermann.figmaDesignTokens": {
            "styleId": "S:f1958201bdf6881f8964c169c4cd0a6565836f73,",
            "exportKey": "color"
          }
        }
      },
      "600": {
        "description": "",
        "type": "color",
        "value": "#475467ff",
        "blendMode": "normal",
        "extensions": {
          "org.lukasoppermann.figmaDesignTokens": {
            "styleId": "S:e3f0192ef6527b44f73f06fad713e6738c0cfd23,",
            "exportKey": "color"
          }
        }
      },
      "700": {
        "description": "",
        "type": "color",
        "value": "#344054ff",
        "blendMode": "normal",
        "extensions": {
          "org.lukasoppermann.figmaDesignTokens": {
            "styleId": "S:5a9d1bb0ed54dacbda3cc29afcc99ae4bc557bb4,",
            "exportKey": "color"
          }
        }
      },
      "800": {
        "description": "",
        "type": "color",
        "value": "#1d2939ff",
        "blendMode": "normal",
        "extensions": {
          "org.lukasoppermann.figmaDesignTokens": {
            "styleId": "S:a77666b900a5fe04591bff9e735a3144e1d9f363,",
            "exportKey": "color"
          }
        }
      },
      "900": {
        "description": "",
        "type": "color",
        "value": "#101828ff",
        "blendMode": "normal",
        "extensions": {
          "org.lukasoppermann.figmaDesignTokens": {
            "styleId": "S:07fc06cc426f9513be5acfc4d1e589af7c909157,",
            "exportKey": "color"
          }
        }
      }
    }
  },
  "font": {
    "typo": {
      "2xlarge": {
        "type": "custom-fontStyle",
        "value": {
          "fontSize": 72,
          "textDecoration": "none",
          "fontFamily": "Inter",
          "fontWeight": 700,
          "fontStyle": "normal",
          "fontStretch": "normal",
          "letterSpacing": -1.44,
          "lineHeight": 90,
          "paragraphIndent": 0,
          "paragraphSpacing": 72,
          "textCase": "capitalize"
        },
        "extensions": {
          "org.lukasoppermann.figmaDesignTokens": {
            "styleId": "S:e9bf4ac1c44a86300de65539b951c2c97138f229,",
            "exportKey": "font"
          }
        }
      }
    },
    "fontFamilies": {
      "inter": {
        "value": "Inter",
        "type": "fontFamilies"
      }
    },
    "lineHeights": {
      "0": {
        "value": "90",
        "type": "lineHeights"
      },
      "1": {
        "value": "72",
        "type": "lineHeights"
      },
      "2": {
        "value": "60",
        "type": "lineHeights"
      },
      "3": {
        "value": "44",
        "type": "lineHeights"
      },
      "4": {
        "value": "38",
        "type": "lineHeights"
      },
      "5": {
        "value": "32",
        "type": "lineHeights"
      },
      "6": {
        "value": "30",
        "type": "lineHeights"
      },
      "7": {
        "value": "28",
        "type": "lineHeights"
      },
      "8": {
        "value": "24",
        "type": "lineHeights"
      },
      "9": {
        "value": "20",
        "type": "lineHeights"
      },
      "10": {
        "value": "18",
        "type": "lineHeights"
      }
    },
    "fontWeights": {
      "inter-0": {
        "value": "Bold",
        "type": "fontWeights"
      },
      "inter-1": {
        "value": "Semi Bold",
        "type": "fontWeights"
      },
      "inter-2": {
        "value": "Medium",
        "type": "fontWeights"
      },
      "inter-3": {
        "value": "Regular",
        "type": "fontWeights"
      }
    },
    "fontSize": {
      "0": {
        "value": "12",
        "type": "fontSizes"
      },
      "1": {
        "value": "14",
        "type": "fontSizes"
      },
      "2": {
        "value": "16",
        "type": "fontSizes"
      },
      "3": {
        "value": "18",
        "type": "fontSizes"
      },
      "4": {
        "value": "20",
        "type": "fontSizes"
      },
      "5": {
        "value": "24",
        "type": "fontSizes"
      },
      "6": {
        "value": "30",
        "type": "fontSizes"
      },
      "7": {
        "value": "36",
        "type": "fontSizes"
      },
      "8": {
        "value": "48",
        "type": "fontSizes"
      },
      "9": {
        "value": "60",
        "type": "fontSizes"
      },
      "10": {
        "value": "72",
        "type": "fontSizes"
      }
    },
    "letterSpacing": {
      "0": {
        "value": "-2%",
        "type": "letterSpacing"
      },
      "1": {
        "value": "0%",
        "type": "letterSpacing"
      }
    },
    "paragraphSpacing": {
      "0": {
        "value": "12",
        "type": "paragraphSpacing"
      },
      "1": {
        "value": "14",
        "type": "paragraphSpacing"
      },
      "2": {
        "value": "16",
        "type": "paragraphSpacing"
      },
      "3": {
        "value": "18",
        "type": "paragraphSpacing"
      },
      "4": {
        "value": "20",
        "type": "paragraphSpacing"
      },
      "5": {
        "value": "24",
        "type": "paragraphSpacing"
      },
      "6": {
        "value": "30",
        "type": "paragraphSpacing"
      },
      "7": {
        "value": "36",
        "type": "paragraphSpacing"
      },
      "8": {
        "value": "48",
        "type": "paragraphSpacing"
      },
      "9": {
        "value": "60",
        "type": "paragraphSpacing"
      },
      "10": {
        "value": "72",
        "type": "paragraphSpacing"
      }
    },
    "Typo": {
      "2XLarge": {
        "value": {
          "fontFamily": "{fontFamilies.inter}",
          "fontWeight": "{fontWeights.inter-0}",
          "lineHeight": "{lineHeights.0}",
          "fontSize": "{fontSize.10}",
          "letterSpacing": "{letterSpacing.0}",
          "paragraphSpacing": "{paragraphSpacing.10}",
          "textCase": "{textCase.capitalize}",
          "textDecoration": "{textDecoration.none}"
        },
        "type": "typography"
      },
      "XLarge": {
        "value": {
          "fontFamily": "{fontFamilies.inter}",
          "fontWeight": "{fontWeights.inter-1}",
          "lineHeight": "{lineHeights.1}",
          "fontSize": "{fontSize.9}",
          "letterSpacing": "{letterSpacing.0}",
          "paragraphSpacing": "{paragraphSpacing.9}",
          "textCase": "{textCase.capitalize}",
          "textDecoration": "{textDecoration.none}"
        },
        "type": "typography"
      },
      "Large": {
        "value": {
          "fontFamily": "{fontFamilies.inter}",
          "fontWeight": "{fontWeights.inter-1}",
          "lineHeight": "{lineHeights.2}",
          "fontSize": "{fontSize.8}",
          "letterSpacing": "{letterSpacing.0}",
          "paragraphSpacing": "{paragraphSpacing.8}",
          "textCase": "{textCase.capitalize}",
          "textDecoration": "{textDecoration.none}"
        },
        "type": "typography"
      },
      "Medium": {
        "value": {
          "fontFamily": "{fontFamilies.inter}",
          "fontWeight": "{fontWeights.inter-1}",
          "lineHeight": "{lineHeights.3}",
          "fontSize": "{fontSize.7}",
          "letterSpacing": "{letterSpacing.0}",
          "paragraphSpacing": "{paragraphSpacing.7}",
          "textCase": "{textCase.capitalize}",
          "textDecoration": "{textDecoration.none}"
        },
        "type": "typography"
      },
      "H1": {
        "value": {
          "fontFamily": "{fontFamilies.inter}",
          "fontWeight": "{fontWeights.inter-1}",
          "lineHeight": "{lineHeights.4}",
          "fontSize": "{fontSize.6}",
          "letterSpacing": "{letterSpacing.1}",
          "paragraphSpacing": "{paragraphSpacing.6}",
          "textCase": "{textCase.capitalize}",
          "textDecoration": "{textDecoration.none}"
        },
        "type": "typography"
      },
      "H2": {
        "value": {
          "fontFamily": "{fontFamilies.inter}",
          "fontWeight": "{fontWeights.inter-1}",
          "lineHeight": "{lineHeights.5}",
          "fontSize": "{fontSize.5}",
          "letterSpacing": "{letterSpacing.1}",
          "paragraphSpacing": "{paragraphSpacing.5}",
          "textCase": "{textCase.capitalize}",
          "textDecoration": "{textDecoration.none}"
        },
        "type": "typography"
      },
      "H3": {
        "value": {
          "fontFamily": "{fontFamilies.inter}",
          "fontWeight": "{fontWeights.inter-1}",
          "lineHeight": "{lineHeights.6}",
          "fontSize": "{fontSize.4}",
          "letterSpacing": "{letterSpacing.1}",
          "paragraphSpacing": "{paragraphSpacing.4}",
          "textCase": "{textCase.capitalize}",
          "textDecoration": "{textDecoration.none}"
        },
        "type": "typography"
      },
      "H4": {
        "value": {
          "fontFamily": "{fontFamilies.inter}",
          "fontWeight": "{fontWeights.inter-1}",
          "lineHeight": "{lineHeights.7}",
          "fontSize": "{fontSize.3}",
          "letterSpacing": "{letterSpacing.1}",
          "paragraphSpacing": "{paragraphSpacing.3}",
          "textCase": "{textCase.capitalize}",
          "textDecoration": "{textDecoration.none}"
        },
        "type": "typography"
      },
      "H5": {
        "value": {
          "fontFamily": "{fontFamilies.inter}",
          "fontWeight": "{fontWeights.inter-2}",
          "lineHeight": "{lineHeights.8}",
          "fontSize": "{fontSize.2}",
          "letterSpacing": "{letterSpacing.1}",
          "paragraphSpacing": "{paragraphSpacing.2}",
          "textCase": "{textCase.capitalize}",
          "textDecoration": "{textDecoration.none}"
        },
        "type": "typography"
      },
      "Subtitle1": {
        "value": {
          "fontFamily": "{fontFamilies.inter}",
          "fontWeight": "{fontWeights.inter-0}",
          "lineHeight": "{lineHeights.8}",
          "fontSize": "{fontSize.2}",
          "letterSpacing": "{letterSpacing.1}",
          "paragraphSpacing": "{paragraphSpacing.2}",
          "textCase": "{textCase.capitalize}",
          "textDecoration": "{textDecoration.none}"
        },
        "type": "typography"
      },
      "Subtitle2": {
        "value": {
          "fontFamily": "{fontFamilies.inter}",
          "fontWeight": "{fontWeights.inter-0}",
          "lineHeight": "{lineHeights.9}",
          "fontSize": "{fontSize.1}",
          "letterSpacing": "{letterSpacing.1}",
          "paragraphSpacing": "{paragraphSpacing.1}",
          "textCase": "{textCase.capitalize}",
          "textDecoration": "{textDecoration.none}"
        },
        "type": "typography"
      },
      "Body1": {
        "value": {
          "fontFamily": "{fontFamilies.inter}",
          "fontWeight": "{fontWeights.inter-3}",
          "lineHeight": "{lineHeights.8}",
          "fontSize": "{fontSize.2}",
          "letterSpacing": "{letterSpacing.1}",
          "paragraphSpacing": "{paragraphSpacing.2}",
          "textCase": "{textCase.none}",
          "textDecoration": "{textDecoration.none}"
        },
        "type": "typography"
      },
      "Body2": {
        "value": {
          "fontFamily": "{fontFamilies.inter}",
          "fontWeight": "{fontWeights.inter-3}",
          "lineHeight": "{lineHeights.9}",
          "fontSize": "{fontSize.1}",
          "letterSpacing": "{letterSpacing.1}",
          "paragraphSpacing": "{paragraphSpacing.1}",
          "textCase": "{textCase.none}",
          "textDecoration": "{textDecoration.none}"
        },
        "type": "typography"
      },
      "Button1": {
        "value": {
          "fontFamily": "{fontFamilies.inter}",
          "fontWeight": "{fontWeights.inter-1}",
          "lineHeight": "{lineHeights.8}",
          "fontSize": "{fontSize.1}",
          "letterSpacing": "{letterSpacing.1}",
          "paragraphSpacing": "{paragraphSpacing.2}",
          "textCase": "{textCase.capitalize}",
          "textDecoration": "{textDecoration.none}"
        },
        "type": "typography"
      },
      "Button2": {
        "value": {
          "fontFamily": "{fontFamilies.inter}",
          "fontWeight": "{fontWeights.inter-2}",
          "lineHeight": "{lineHeights.9}",
          "fontSize": "{fontSize.0}",
          "letterSpacing": "{letterSpacing.1}",
          "paragraphSpacing": "{paragraphSpacing.1}",
          "textCase": "{textCase.capitalize}",
          "textDecoration": "{textDecoration.none}"
        },
        "type": "typography"
      },
      "Label": {
        "value": {
          "fontFamily": "{fontFamilies.inter}",
          "fontWeight": "{fontWeights.inter-1}",
          "lineHeight": "{lineHeights.10}",
          "fontSize": "{fontSize.0}",
          "letterSpacing": "{letterSpacing.1}",
          "paragraphSpacing": "{paragraphSpacing.0}",
          "textCase": "{textCase.capitalize}",
          "textDecoration": "{textDecoration.none}"
        },
        "type": "typography"
      },
      "Caption": {
        "value": {
          "fontFamily": "{fontFamilies.inter}",
          "fontWeight": "{fontWeights.inter-3}",
          "lineHeight": "{lineHeights.10}",
          "fontSize": "{fontSize.0}",
          "letterSpacing": "{letterSpacing.1}",
          "paragraphSpacing": "{paragraphSpacing.0}",
          "textCase": "{textCase.none}",
          "textDecoration": "{textDecoration.none}"
        },
        "type": "typography"
      }
    },
    "textCase": {
      "capitalize": {
        "value": "capitalize",
        "type": "textCase"
      },
      "none": {
        "value": "none",
        "type": "textCase"
      }
    },
    "textDecoration": {
      "none": {
        "value": "none",
        "type": "textDecoration"
      }
    }
  },
  "typography": {
    "typo": {
      "2xlarge": {
        "fontSize": {
          "type": "dimension",
          "value": 72
        },
        "textDecoration": {
          "type": "string",
          "value": "none"
        },
        "fontFamily": {
          "type": "string",
          "value": "Inter"
        },
        "fontWeight": {
          "type": "number",
          "value": 700
        },
        "fontStyle": {
          "type": "string",
          "value": "normal"
        },
        "fontStretch": {
          "type": "string",
          "value": "normal"
        },
        "letterSpacing": {
          "type": "dimension",
          "value": -1.44
        },
        "lineHeight": {
          "type": "dimension",
          "value": 90
        },
        "paragraphIndent": {
          "type": "dimension",
          "value": 0
        },
        "paragraphSpacing": {
          "type": "dimension",
          "value": 72
        },
        "textCase": {
          "type": "string",
          "value": "capitalize"
        }
      }
    }
  },
  "main": {
    "Link": {
      "25": {
        "value": "#f5faff",
        "type": "color"
      },
      "50": {
        "value": "#eff8ff",
        "type": "color"
      },
      "100": {
        "value": "#d1e9ff",
        "type": "color"
      },
      "200": {
        "value": "#b2ddff",
        "type": "color"
      },
      "300": {
        "value": "#84caff",
        "type": "color"
      },
      "400": {
        "value": "#53b1fd",
        "type": "color"
      },
      "500": {
        "value": "#2e90fa",
        "type": "color"
      },
      "600": {
        "value": "#1570ef",
        "type": "color"
      },
      "700": {
        "value": "#175cd3",
        "type": "color"
      },
      "800": {
        "value": "#1849a9",
        "type": "color"
      },
      "900": {
        "value": "#194185",
        "type": "color"
      }
    },
    "Success": {
      "25": {
        "value": "#f6fef9",
        "type": "color"
      },
      "50": {
        "value": "#ecfdf3",
        "type": "color"
      },
      "100": {
        "value": "#d1fadf",
        "type": "color"
      },
      "200": {
        "value": "#a6f4c5",
        "type": "color"
      },
      "300": {
        "value": "#6ce9a6",
        "type": "color"
      },
      "400": {
        "value": "#32d583",
        "type": "color"
      },
      "500": {
        "value": "#12b76a",
        "type": "color"
      },
      "600": {
        "value": "#039855",
        "type": "color"
      },
      "700": {
        "value": "#027a48",
        "type": "color"
      },
      "800": {
        "value": "#05603a",
        "type": "color"
      },
      "900": {
        "value": "#054f31",
        "type": "color"
      }
    },
    "Warning": {
      "25": {
        "value": "#fffcf5",
        "type": "color"
      },
      "50": {
        "value": "#fffaeb",
        "type": "color"
      },
      "100": {
        "value": "#fef0c7",
        "type": "color"
      },
      "200": {
        "value": "#fedf89",
        "type": "color"
      },
      "300": {
        "value": "#fec84b",
        "type": "color"
      },
      "400": {
        "value": "#fdb022",
        "type": "color"
      },
      "500": {
        "value": "#f79009",
        "type": "color"
      },
      "600": {
        "value": "#dc6803",
        "type": "color"
      },
      "700": {
        "value": "#b54708",
        "type": "color"
      },
      "800": {
        "value": "#93370d",
        "type": "color"
      },
      "900": {
        "value": "#7a2e0e",
        "type": "color"
      }
    },
    "Error": {
      "25": {
        "value": "#fffbfa",
        "type": "color"
      },
      "50": {
        "value": "#fef3f2",
        "type": "color"
      },
      "100": {
        "value": "#fee4e2",
        "type": "color"
      },
      "200": {
        "value": "#fecdca",
        "type": "color"
      },
      "300": {
        "value": "#fda29b",
        "type": "color"
      },
      "400": {
        "value": "#f97066",
        "type": "color"
      },
      "500": {
        "value": "#f04438",
        "type": "color"
      },
      "600": {
        "value": "#d92d20",
        "type": "color"
      },
      "700": {
        "value": "#b42318",
        "type": "color"
      },
      "800": {
        "value": "#912018",
        "type": "color"
      },
      "900": {
        "value": "#7a271a",
        "type": "color"
      }
    },
    "Primary": {
      "25": {
        "value": "#fffcf2",
        "type": "color"
      },
      "50": {
        "value": "#fef8dd",
        "type": "color"
      },
      "100": {
        "value": "#fef5cb",
        "type": "color"
      },
      "200": {
        "value": "#ffeb74",
        "type": "color"
      },
      "300": {
        "value": "#ffdd00",
        "type": "color"
      },
      "400": {
        "value": "#f9ca02",
        "type": "color"
      },
      "500": {
        "value": "#f2b705",
        "type": "color"
      },
      "600": {
        "value": "#f0b305",
        "type": "color"
      },
      "700": {
        "value": "#e9a405",
        "type": "color"
      },
      "800": {
        "value": "#e29606",
        "type": "color"
      },
      "900": {
        "value": "#d17407",
        "type": "color"
      }
    },
    "Gray": {
      "25": {
        "value": "#fcfcfd",
        "type": "color"
      },
      "50": {
        "value": "#f9fafb",
        "type": "color"
      },
      "100": {
        "value": "#f2f4f7",
        "type": "color"
      },
      "200": {
        "value": "#eaecf0",
        "type": "color"
      },
      "300": {
        "value": "#d0d5dd",
        "type": "color"
      },
      "400": {
        "value": "#98a2b3",
        "type": "color"
      },
      "500": {
        "value": "#667085",
        "type": "color"
      },
      "600": {
        "value": "#475467",
        "type": "color"
      },
      "700": {
        "value": "#344054",
        "type": "color"
      },
      "800": {
        "value": "#1d2939",
        "type": "color"
      },
      "900": {
        "value": "#101828",
        "type": "color"
      }
    },
    "fontFamilies": {
      "inter": {
        "value": "Inter",
        "type": "fontFamilies"
      }
    },
    "lineHeights": {
      "0": {
        "value": "90",
        "type": "lineHeights"
      },
      "1": {
        "value": "72",
        "type": "lineHeights"
      },
      "2": {
        "value": "60",
        "type": "lineHeights"
      },
      "3": {
        "value": "44",
        "type": "lineHeights"
      },
      "4": {
        "value": "38",
        "type": "lineHeights"
      },
      "5": {
        "value": "32",
        "type": "lineHeights"
      },
      "6": {
        "value": "30",
        "type": "lineHeights"
      },
      "7": {
        "value": "28",
        "type": "lineHeights"
      },
      "8": {
        "value": "24",
        "type": "lineHeights"
      },
      "9": {
        "value": "20",
        "type": "lineHeights"
      },
      "10": {
        "value": "18",
        "type": "lineHeights"
      }
    },
    "fontWeights": {
      "inter-0": {
        "value": "Bold",
        "type": "fontWeights"
      },
      "inter-1": {
        "value": "Semi Bold",
        "type": "fontWeights"
      },
      "inter-2": {
        "value": "Medium",
        "type": "fontWeights"
      },
      "inter-3": {
        "value": "Regular",
        "type": "fontWeights"
      }
    },
    "fontSize": {
      "0": {
        "value": "12",
        "type": "fontSizes"
      },
      "1": {
        "value": "14",
        "type": "fontSizes"
      },
      "2": {
        "value": "16",
        "type": "fontSizes"
      },
      "3": {
        "value": "18",
        "type": "fontSizes"
      },
      "4": {
        "value": "20",
        "type": "fontSizes"
      },
      "5": {
        "value": "24",
        "type": "fontSizes"
      },
      "6": {
        "value": "30",
        "type": "fontSizes"
      },
      "7": {
        "value": "36",
        "type": "fontSizes"
      },
      "8": {
        "value": "48",
        "type": "fontSizes"
      },
      "9": {
        "value": "60",
        "type": "fontSizes"
      },
      "10": {
        "value": "72",
        "type": "fontSizes"
      }
    },
    "letterSpacing": {
      "0": {
        "value": "-2%",
        "type": "letterSpacing"
      },
      "1": {
        "value": "0%",
        "type": "letterSpacing"
      }
    },
    "paragraphSpacing": {
      "0": {
        "value": "12",
        "type": "paragraphSpacing"
      },
      "1": {
        "value": "14",
        "type": "paragraphSpacing"
      },
      "2": {
        "value": "16",
        "type": "paragraphSpacing"
      },
      "3": {
        "value": "18",
        "type": "paragraphSpacing"
      },
      "4": {
        "value": "20",
        "type": "paragraphSpacing"
      },
      "5": {
        "value": "24",
        "type": "paragraphSpacing"
      },
      "6": {
        "value": "30",
        "type": "paragraphSpacing"
      },
      "7": {
        "value": "36",
        "type": "paragraphSpacing"
      },
      "8": {
        "value": "48",
        "type": "paragraphSpacing"
      },
      "9": {
        "value": "60",
        "type": "paragraphSpacing"
      },
      "10": {
        "value": "72",
        "type": "paragraphSpacing"
      }
    },
    "Typo": {
      "2XLarge": {
        "value": {
          "fontFamily": "{fontFamilies.inter}",
          "fontWeight": "{fontWeights.inter-0}",
          "lineHeight": "{lineHeights.0}",
          "fontSize": "{fontSize.10}",
          "letterSpacing": "{letterSpacing.0}",
          "paragraphSpacing": "{paragraphSpacing.10}",
          "textCase": "{textCase.capitalize}",
          "textDecoration": "{textDecoration.none}"
        },
        "type": "typography"
      },
      "XLarge": {
        "value": {
          "fontFamily": "{fontFamilies.inter}",
          "fontWeight": "{fontWeights.inter-1}",
          "lineHeight": "{lineHeights.1}",
          "fontSize": "{fontSize.9}",
          "letterSpacing": "{letterSpacing.0}",
          "paragraphSpacing": "{paragraphSpacing.9}",
          "textCase": "{textCase.capitalize}",
          "textDecoration": "{textDecoration.none}"
        },
        "type": "typography"
      },
      "Large": {
        "value": {
          "fontFamily": "{fontFamilies.inter}",
          "fontWeight": "{fontWeights.inter-1}",
          "lineHeight": "{lineHeights.2}",
          "fontSize": "{fontSize.8}",
          "letterSpacing": "{letterSpacing.0}",
          "paragraphSpacing": "{paragraphSpacing.8}",
          "textCase": "{textCase.capitalize}",
          "textDecoration": "{textDecoration.none}"
        },
        "type": "typography"
      },
      "Medium": {
        "value": {
          "fontFamily": "{fontFamilies.inter}",
          "fontWeight": "{fontWeights.inter-1}",
          "lineHeight": "{lineHeights.3}",
          "fontSize": "{fontSize.7}",
          "letterSpacing": "{letterSpacing.0}",
          "paragraphSpacing": "{paragraphSpacing.7}",
          "textCase": "{textCase.capitalize}",
          "textDecoration": "{textDecoration.none}"
        },
        "type": "typography"
      },
      "H1": {
        "value": {
          "fontFamily": "{fontFamilies.inter}",
          "fontWeight": "{fontWeights.inter-1}",
          "lineHeight": "{lineHeights.4}",
          "fontSize": "{fontSize.6}",
          "letterSpacing": "{letterSpacing.1}",
          "paragraphSpacing": "{paragraphSpacing.6}",
          "textCase": "{textCase.capitalize}",
          "textDecoration": "{textDecoration.none}"
        },
        "type": "typography"
      },
      "H2": {
        "value": {
          "fontFamily": "{fontFamilies.inter}",
          "fontWeight": "{fontWeights.inter-1}",
          "lineHeight": "{lineHeights.5}",
          "fontSize": "{fontSize.5}",
          "letterSpacing": "{letterSpacing.1}",
          "paragraphSpacing": "{paragraphSpacing.5}",
          "textCase": "{textCase.capitalize}",
          "textDecoration": "{textDecoration.none}"
        },
        "type": "typography"
      },
      "H3": {
        "value": {
          "fontFamily": "{fontFamilies.inter}",
          "fontWeight": "{fontWeights.inter-1}",
          "lineHeight": "{lineHeights.6}",
          "fontSize": "{fontSize.4}",
          "letterSpacing": "{letterSpacing.1}",
          "paragraphSpacing": "{paragraphSpacing.4}",
          "textCase": "{textCase.capitalize}",
          "textDecoration": "{textDecoration.none}"
        },
        "type": "typography"
      },
      "H4": {
        "value": {
          "fontFamily": "{fontFamilies.inter}",
          "fontWeight": "{fontWeights.inter-1}",
          "lineHeight": "{lineHeights.7}",
          "fontSize": "{fontSize.3}",
          "letterSpacing": "{letterSpacing.1}",
          "paragraphSpacing": "{paragraphSpacing.3}",
          "textCase": "{textCase.capitalize}",
          "textDecoration": "{textDecoration.none}"
        },
        "type": "typography"
      },
      "H5": {
        "value": {
          "fontFamily": "{fontFamilies.inter}",
          "fontWeight": "{fontWeights.inter-2}",
          "lineHeight": "{lineHeights.8}",
          "fontSize": "{fontSize.2}",
          "letterSpacing": "{letterSpacing.1}",
          "paragraphSpacing": "{paragraphSpacing.2}",
          "textCase": "{textCase.capitalize}",
          "textDecoration": "{textDecoration.none}"
        },
        "type": "typography"
      },
      "Subtitle1": {
        "value": {
          "fontFamily": "{fontFamilies.inter}",
          "fontWeight": "{fontWeights.inter-0}",
          "lineHeight": "{lineHeights.8}",
          "fontSize": "{fontSize.2}",
          "letterSpacing": "{letterSpacing.1}",
          "paragraphSpacing": "{paragraphSpacing.2}",
          "textCase": "{textCase.capitalize}",
          "textDecoration": "{textDecoration.none}"
        },
        "type": "typography"
      },
      "Subtitle2": {
        "value": {
          "fontFamily": "{fontFamilies.inter}",
          "fontWeight": "{fontWeights.inter-0}",
          "lineHeight": "{lineHeights.9}",
          "fontSize": "{fontSize.1}",
          "letterSpacing": "{letterSpacing.1}",
          "paragraphSpacing": "{paragraphSpacing.1}",
          "textCase": "{textCase.capitalize}",
          "textDecoration": "{textDecoration.none}"
        },
        "type": "typography"
      },
      "Body1": {
        "value": {
          "fontFamily": "{fontFamilies.inter}",
          "fontWeight": "{fontWeights.inter-3}",
          "lineHeight": "{lineHeights.8}",
          "fontSize": "{fontSize.2}",
          "letterSpacing": "{letterSpacing.1}",
          "paragraphSpacing": "{paragraphSpacing.2}",
          "textCase": "{textCase.none}",
          "textDecoration": "{textDecoration.none}"
        },
        "type": "typography"
      },
      "Body2": {
        "value": {
          "fontFamily": "{fontFamilies.inter}",
          "fontWeight": "{fontWeights.inter-3}",
          "lineHeight": "{lineHeights.9}",
          "fontSize": "{fontSize.1}",
          "letterSpacing": "{letterSpacing.1}",
          "paragraphSpacing": "{paragraphSpacing.1}",
          "textCase": "{textCase.none}",
          "textDecoration": "{textDecoration.none}"
        },
        "type": "typography"
      },
      "Button1": {
        "value": {
          "fontFamily": "{fontFamilies.inter}",
          "fontWeight": "{fontWeights.inter-1}",
          "lineHeight": "{lineHeights.8}",
          "fontSize": "{fontSize.1}",
          "letterSpacing": "{letterSpacing.1}",
          "paragraphSpacing": "{paragraphSpacing.2}",
          "textCase": "{textCase.capitalize}",
          "textDecoration": "{textDecoration.none}"
        },
        "type": "typography"
      },
      "Button2": {
        "value": {
          "fontFamily": "{fontFamilies.inter}",
          "fontWeight": "{fontWeights.inter-2}",
          "lineHeight": "{lineHeights.9}",
          "fontSize": "{fontSize.0}",
          "letterSpacing": "{letterSpacing.1}",
          "paragraphSpacing": "{paragraphSpacing.1}",
          "textCase": "{textCase.capitalize}",
          "textDecoration": "{textDecoration.none}"
        },
        "type": "typography"
      },
      "Label": {
        "value": {
          "fontFamily": "{fontFamilies.inter}",
          "fontWeight": "{fontWeights.inter-1}",
          "lineHeight": "{lineHeights.10}",
          "fontSize": "{fontSize.0}",
          "letterSpacing": "{letterSpacing.1}",
          "paragraphSpacing": "{paragraphSpacing.0}",
          "textCase": "{textCase.capitalize}",
          "textDecoration": "{textDecoration.none}"
        },
        "type": "typography"
      },
      "Caption": {
        "value": {
          "fontFamily": "{fontFamilies.inter}",
          "fontWeight": "{fontWeights.inter-3}",
          "lineHeight": "{lineHeights.10}",
          "fontSize": "{fontSize.0}",
          "letterSpacing": "{letterSpacing.1}",
          "paragraphSpacing": "{paragraphSpacing.0}",
          "textCase": "{textCase.none}",
          "textDecoration": "{textDecoration.none}"
        },
        "type": "typography"
      }
    },
    "textCase": {
      "capitalize": {
        "value": "capitalize",
        "type": "textCase"
      },
      "none": {
        "value": "none",
        "type": "textCase"
      }
    },
    "textDecoration": {
      "none": {
        "value": "none",
        "type": "textDecoration"
      }
    }
  },
  "$themes": [],
  "$metadata": {
    "tokenSetOrder": [
      "color",
      "font",
      "typography",
      "main"
    ]
  }
}